llama_index/tools/python_file/__init__.py
llama_index/tools/python_file/base.py
llama_index_tools_python_file-0.4.1.dist-info/METADATA
llama_index_tools_python_file-0.4.1.dist-info/WHEEL
llama_index_tools_python_file-0.4.1.dist-info/licenses/LICENSE
llama_index_tools_python_file-0.4.1.dist-info/RECORD
